zerotier_api_cli/__init__.py
zerotier_api_cli/__main__.py
zerotier_api_cli/_api.py
zerotier_api_cli/_cli.py
zerotier_api_cli/_config.py
zerotier_api_cli-0.1.1.dist-info/LICENSE
zerotier_api_cli-0.1.1.dist-info/METADATA
zerotier_api_cli-0.1.1.dist-info/WHEEL
zerotier_api_cli-0.1.1.dist-info/entry_points.txt
zerotier_api_cli-0.1.1.dist-info/RECORD
