Metadata-Version: 2.3
Name: zerotier-api-cli
Version: 0.1.1
Summary: A command-line interface for managing ZeroTier networks, built with Python.
License: MIT
Author: Kaj Siebert
Author-email: kaj@k-si.com
Requires-Python: >=3.10
Classifier: License :: OSI Approved :: MIT License
Classifier: Programming Language :: Python :: 3
Classifier: Programming Language :: Python :: 3.10
Classifier: Programming Language :: Python :: 3.11
Classifier: Programming Language :: Python :: 3.12
Classifier: Programming Language :: Python :: 3.13
Requires-Dist: click (>=8.1.8,<9.0.0)
Requires-Dist: click-log (>=0.4.0,<0.5.0)
Requires-Dist: dotenv (>=0.9.9,<0.10.0)
Requires-Dist: humanize (>=4.9.0,<5.0.0)
Requires-Dist: platformdirs (>=4.3.7,<5.0.0)
Requires-Dist: pyyaml (>=6.0.2,<7.0.0)
Requires-Dist: requests (>=2.32.3,<3.0.0)
Requires-Dist: rich (>=14.0.0,<15.0.0)
